{
"type": "FeatureCollection",
"name": "2000_accumulate",
"crs": { "type": "name", "properties": { "name": "urn:ogc:def:crs:OGC:1.3:CRS84" } },
"features": [
{ "type": "Feature", "properties": { "Name": "James A. Fallenbeck and Martha H. Fallenbeck - Deed of Trust", "Released Date": "9/18/2014", "Bonding Company": "Bail USA", "Amount_String": "$110,000 ", "Signed Date": "4/12/2000", "Street Number": 6305.0, "Street": "Hanna Court", "Apt. #": null, "City": "Charlotte", "Zip": 28212.0, "Formula Complete Address": "6305 Hanna Court, Charlotte North Carolina 2812", "Latitude": 35.21764398, "Longitude": -80.7514293, "Foreclosed Date": null, "Lien Duration": 5272.0, "Status": "Released", "Year Signed": 2000.0, "Year Released": 2014.0, "Year Foreclosed": 9999, "Status Per Year": "Signed That Year", "Amount": 110000 }, "geometry": { "type": "Point", "coordinates": [ -80.7514293, 35.21764398 ] } },
{ "type": "Feature", "properties": { "Name": "James A. Fallenbeck and Martha Fallenbeck - Subordination of Deed of Trust", "Released Date": "9/18/2014", "Bonding Company": "Bail USA", "Amount_String": "$110,000 ", "Signed Date": "7/13/2000", "Street Number": null, "Street": null, "Apt. #": null, "City": null, "Zip": null, "Formula Complete Address": null, "Latitude": null, "Longitude": null, "Foreclosed Date": null, "Lien Duration": 5180.0, "Status": "Released", "Year Signed": 2000.0, "Year Released": 2014.0, "Year Foreclosed": 9999, "Status Per Year": "Signed That Year", "Amount": 110000 }, "geometry": null },
{ "type": "Feature", "properties": { "Name": "James T. Nixon and Lucinda K. Nixon - Mortgage Agreement", "Released Date": null, "Bonding Company": "Bankers Insurance", "Amount_String": "$105,000 ", "Signed Date": "8/9/2000", "Street Number": 6009.0, "Street": "Black Bear Court", "Apt. #": null, "City": "Charlotte", "Zip": 28214.0, "Formula Complete Address": "6009 Black Bear Ct., Charlotte, NC 28214", "Latitude": 35.26128404, "Longitude": -80.94836543, "Foreclosed Date": null, "Lien Duration": 8180.0, "Status": "Pending", "Year Signed": 2000.0, "Year Released": 9999.0, "Year Foreclosed": 9999, "Status Per Year": "Signed That Year", "Amount": 105000 }, "geometry": { "type": "Point", "coordinates": [ -80.94836543, 35.26128404 ] } }
]
}
