{
"type": "FeatureCollection",
"name": "2004_accumulate",
"crs": { "type": "name", "properties": { "name": "urn:ogc:def:crs:OGC:1.3:CRS84" } },
"features": [
{ "type": "Feature", "properties": { "Last": "Hagan", "First": "Richard S", "Co-Last": "Hagan", "Co-First": "Cheryl", "Satisfactions": null, "Book": "M", "Vol": 23446, "Page": 60, "Date Recorded": "10/08/2002", "Date Released": null, "Criminal Record PDF": null, "DF Last": "Hagan", "DF First": "Jennifer", "DF Case OTN No": null, "Bond No.": null, "Bail Co.": "Lexington Natl Ins Corp", "Bail Co. (Mortgagee)": "ABC Bail Bonds Inc Trste", "Amount": 15000, "Date Signed": "7/26/2002", "St. No.": 227, "Street": "Darlan Hill Dr", "Town/Loc": null, "City": "Pittsburgh", "Zip": 15239, "Formula Completing Address": "227 Darlan Hill Dr Pittsburgh 15239", "Latitude": 40.48104376, "Longitude": -79.74348143, "Unnamed: 27": null, "Block": null, "Lot": null, "Field": null, "Satisfactions 2": null, "Geocache Data": "🔵 eyJpIjoiMjI3IERhcmxhbiBIaWxsIERyIFBpdHRzYnVyZ2ggMTUyMzkiLCJvIjp7InN0YXR1cyI6Ik9LIiwiZm9ybWF0dGVkQWRkcmVzcyI6IjIyNyBEYXJsYW4gSGlsbCBEciwgUGl0dHNidXJnaCwgUEEgMTUyMzksIFVTQSIsImxhdCI6NDAuNDgxMDY0LCJsbmciOi03OS43NDM1MTQ1LCJibG9ja0luc3RhbGxhdGlvbklkcyI6WyJibGlQa1ZrRkpPNTJNU2VPMyJdLCJsb2NhdGlvbkZpZWxkSWQiOiJmbGRnNmtwNEM3cmFJRHFSTSJ9LCJlIjoxNjgwNzQ2Njc0MDMyfQ==", "Sex": null, "Race": null, "Arrest Date": null, "Confinement Date": null, "Confinement End": null, "Calculation": null, "Initiation Date": null, "Bail Set Date": null, "Bail Posted Date": null, "Comment": null, "Zapier Trigger": "9/15/2021 11:31am", "Doc No.": 162578, "Bail Lien PDF": "Hagan.tif (https://v5.airtableusercontent.com/v2/22/22/1699005600000/00DOWCRvxlKFSy9Kgzu0gA/E4myZlSdCii_wCrwcVJTLw-kz-kgzqoJvdkikbJnIUzs-BRH4XO6zZ0NA8Kwq8Dc86NaYE95_pXxdURTaTELmGK-BzwBFoP5iHYELte6l-l7GRI8V_WrqiwHuywEdVm_BEBSOvL84cqSVThgrBt_cg/kDe_XdyE2XgT9gaqmMRNdK6QXWuDgmVNO-G7j7inn8Y),Hagan_result.pdf (https://v5.airtableusercontent.com/v2/22/22/1699005600000/KEnGWSfOS2mcGa93XA4XNQ/B2bKDI3lzMVNlW4ohJOutPLHTHHJb0M543DJHabTAZR-qpSp5JT8VprKEuLySisBvipw8UxGmCDLaeKrOIzsNM8TD3SD8-aaXoCNKLfLuWR3psO6BopRC5oNFAdItEHzpWhm6iEDf17ygBZvN7-6nlJxhZ7eSJtSNsDl24mV7Kw/wDzMRh5jYkYtXaR2tp45afOU-dwDAOP__xm-XNcXuqU)", "PDF Copy": "162578.pdf (https://v5.airtableusercontent.com/v2/22/22/1699005600000/PEGnIXxQK5NFqmUQX_kF2g/iuLIb3cWzXiAY6TJZIEF-aWE0pknKdUAZUhQOij5xYeExpIqi4KD5JwoXdpUb5gxX9uVWdSUJ1Ux5Qem7phR_jh4m9gtxmKdZckSECvPfWqAflVRzC4KAxaHFsi-1JBmw9CJhOWFuiaHclX8t3nCxQ/8rumzMPJ-xVH25euuaEHqOGayUGNfosaEezRnbGcUag)", "Convert to PDF": "checked", "Lien Duration": 7464, "Lien Duration By Year": 20.44931507, "Status": "Pending", "Year Signed": 2002, "Year Released": 9999, "Status Per Year": "Pending", "Status Per Year1": "Pending" }, "geometry": { "type": "Point", "coordinates": [ -79.74348143, 40.48104376 ] } },
{ "type": "Feature", "properties": { "Last": "Woznichak", "First": "Christine", "Co-Last": "Woznichak", "Co-First": "Lawrence", "Satisfactions": null, "Book": "M", "Vol": 23043, "Page": 399, "Date Recorded": "7/26/2002", "Date Released": null, "Criminal Record PDF": null, "DF Last": "Casterton", "DF First": "John William", "DF Case OTN No": null, "Bond No.": null, "Bail Co.": "Action Bail Bonds Inc.", "Bail Co. (Mortgagee)": "Bankers Surety", "Amount": 40000, "Date Signed": "8/29/2001", "St. No.": 26, "Street": "Cabindale Dr.", "Town/Loc": "Kennedy TP", "City": "Mckees Rocks", "Zip": 15136, "Formula Completing Address": "26 Cabindale Dr. Mckees Rocks 15136", "Latitude": 40.47670616, "Longitude": -80.1051029, "Unnamed: 27": null, "Block": "0155-L", "Lot": 154, "Field": null, "Satisfactions 2": null, "Geocache Data": "🔵 eyJpIjoiMjYgQ2FiaW5kYWxlIERyLiBNY2tlZXMgUm9ja3MgMTUxMzYiLCJvIjp7InN0YXR1cyI6Ik9LIiwiZm9ybWF0dGVkQWRkcmVzcyI6IjI2IENhYmluZGFsZSBEciwgTWNLZWVzIFJvY2tzLCBQQSAxNTEzNiwgVVNBIiwibGF0Ijo0MC40NzY3MjI1LCJsbmciOi04MC4xMDUxMDI4OTk5OTk5OSwiYmxvY2tJbnN0YWxsYXRpb25JZHMiOlsiYmxpUGtWa0ZKTzUyTVNlTzMiXSwibG9jYXRpb25GaWVsZElkIjoiZmxkZzZrcDRDN3JhSURxUk0ifSwiZSI6MTY4MDc0NjcyMjQxM30=", "Sex": null, "Race": null, "Arrest Date": null, "Confinement Date": null, "Confinement End": null, "Calculation": null, "Initiation Date": null, "Bail Set Date": null, "Bail Posted Date": null, "Comment": null, "Zapier Trigger": null, "Doc No.": 119835, "Bail Lien PDF": null, "PDF Copy": null, "Convert to PDF": null, "Lien Duration": 7795, "Lien Duration By Year": 21.35616438, "Status": "Pending", "Year Signed": 2001, "Year Released": 9999, "Status Per Year": "Pending", "Status Per Year1": "Pending" }, "geometry": { "type": "Point", "coordinates": [ -80.1051029, 40.47670616 ] } }
]
}
