{
"type": "FeatureCollection",
"name": "2001_accumulate",
"crs": { "type": "name", "properties": { "name": "urn:ogc:def:crs:EPSG::3857" } },
"features": [
{ "type": "Feature", "properties": { "Name": "Willie Adams - Trust Deed and Note Securing Bail Bond", "Document #": 573582.0, "Lien Document": "573582.pdf (https://v5.airtableusercontent.com/v3/u/31/31/1723514400000/pkAY_EgOjNlr8uFoOuoBTg/tfFUYllxI9-fVQGL1UUXgBtpw8BYhz7PMz6O_t9GNTwnpJYMKYef-XlWpHEGQMk_Iy6ju7j5nGvcvTJGxiL3FBxosGizvcMZejd_6tDOi-JvGwDAJKWEKyv5xws4KmwcuG-eAB-fyMZbPlyE9qmkdg/QjLqusSBQW8cT4O3Kd5eRgEfjGpktgSvcO2QcoLPWl4)", "Bond Number": "2001-DD2518", "Bonding Company": "ABC Bail Bonds", "Amount_String": "$25,000.00 ", "Signed Date": "11/9/2001", "Street Number": 98, "Street Name": "Montrose Street", "Apt. Number": null, "City": "Newark", "Zip": 7106.0, "Formula Completing Street Address": "98 Montrose Street   Newark 07106", "Longitude": -74.2387618, "Latitude": 40.7421661, "Lot": null, "Block": null, "Released Date": "9/29/2009", "Foreclosed Date": null, "Lien Duration": 2881.0, "Status": "Released", "Year Signed": 2001.0, "Year Released": 2009.0, "Year Foreclosed": 9999, "Status Per Year": "Signed That Year", "Amount": 2500000 }, "geometry": { "type": "Point", "coordinates": [ -74.2387618, 40.7421661 ] } },
{ "type": "Feature", "properties": { "Name": "Betty Miles - Trust Deed and Note Securing Bail Bond", "Document #": 558352.0, "Lien Document": "558352.pdf (https://v5.airtableusercontent.com/v3/u/31/31/1723514400000/A_QVbApJzvAJKL1PA8FbwQ/OjTEyirtY0zG_fxHVFLkXDBsULcBJ-kCP3PB1Xz9VTOztAqmHZ_nYNpJ1dMQZqK37WMJ67AaCSfKy3nxuEnFdGnm-Sj0Qa7UJ9ia8Jm7jtUCRAfUOSyskhZ-ggd_qzj5DW5NgK2-191CpFNXk52PLw/1_u7xVzu6etvWI5eUutRatABdNdTk0aifmzDi8U7_IQ)", "Bond Number": "2001-DD-6011", "Bonding Company": "ABC Bail Bonds", "Amount_String": "$50,000.00 ", "Signed Date": "12/20/2001", "Street Number": 91, "Street Name": "Rose Terrace", "Apt. Number": null, "City": "Newark", "Zip": null, "Formula Completing Street Address": "91 Rose Terrace   Newark ", "Longitude": -74.2035334, "Latitude": 40.7273218, "Lot": null, "Block": null, "Released Date": "3/30/2016", "Foreclosed Date": null, "Lien Duration": 5214.0, "Status": "Released", "Year Signed": 2001.0, "Year Released": 2016.0, "Year Foreclosed": 9999, "Status Per Year": "Signed That Year", "Amount": 5000000 }, "geometry": { "type": "Point", "coordinates": [ -74.2035334, 40.7273218 ] } },
{ "type": "Feature", "properties": { "Name": "Robert Astasio - Trust Deed and Note Securing Bail Bond", "Document #": 419770.0, "Lien Document": "419770.pdf (https://v5.airtableusercontent.com/v3/u/31/31/1723514400000/m90vp9qyQAiaZmD-GsP0Sg/HQb6h9F0N0kiAjdMbIUDazbLTm88MHwgG-WvI20k5XwXE5R3pr_5aXTFa2JX8-SbHtXKRnRIs6wuX0Bei_W5Ue900a5urjJch07oA8PUeqSTYewuRZKpw25xGeYwG1rZKdigJ1FK4bBrz4MKUMY_Vg/P26cIyPCKpmXalV2F0zVqxW0yzyu2Nu6lTE1RjBdWVw)", "Bond Number": "Left blank ", "Bonding Company": "ABC Bail Bonds", "Amount_String": "$50,000.00 ", "Signed Date": "4/6/2001", "Street Number": 230, "Street Name": "Belleville Avenue", "Apt. Number": null, "City": "Belleville", "Zip": 7109.0, "Formula Completing Street Address": "230 Belleville Avenue   Belleville 07109", "Longitude": -74.1592966, "Latitude": 40.7877193, "Lot": null, "Block": null, "Released Date": null, "Foreclosed Date": null, "Lien Duration": 7940.0, "Status": "Pending", "Year Signed": 2001.0, "Year Released": 9999.0, "Year Foreclosed": 9999, "Status Per Year": "Signed That Year", "Amount": 5000000 }, "geometry": { "type": "Point", "coordinates": [ -74.1592966, 40.7877193 ] } }
]
}
